HMMSTUFF/HMMSTUFF.py
HMMSTUFF/logo.jpg
HMMSTUFF/structure_generation.py
HMMSTUFF/models/6HUD/annotationCDR.m
HMMSTUFF/models/6HUD/model.m
HMMSTUFF/models/6HUD/scaler.m
HMMSTUFF/models/6HUD/template_sequence.m
HMMSTUFF/models/6IC3/annotationCDR.m
HMMSTUFF/models/6IC3/model.m
HMMSTUFF/models/6IC3/scaler.m
HMMSTUFF/models/6IC3/template_sequence.m
HMMSTUFF/models/6Z1I/annotationCDR.m
HMMSTUFF/models/6Z1I/model.m
HMMSTUFF/models/6Z1I/scaler.m
HMMSTUFF/models/6Z1I/template_sequence.m
HMMSTUFF/models/6Z1O/annotationCDR.m
HMMSTUFF/models/6Z1O/model.m
HMMSTUFF/models/6Z1O/scaler.m
HMMSTUFF/models/6Z1O/template_sequence.m
HMMSTUFF/models/7NSL/annotationCDR.m
HMMSTUFF/models/7NSL/model.m
HMMSTUFF/models/7NSL/scaler.m
HMMSTUFF/models/7NSL/template_sequence.m
HMMSTUFF/models/8CPE/annotationCDR.m
HMMSTUFF/models/8CPE/model.m
HMMSTUFF/models/8CPE/scaler.m
HMMSTUFF/models/8CPE/template_sequence.m
HMMSTUFF/templates/6HUD.pdb
HMMSTUFF/templates/6IC3.pdb
HMMSTUFF/templates/6Z1I.pdb
HMMSTUFF/templates/6Z1O.pdb
HMMSTUFF/templates/7NSL.pdb
HMMSTUFF/templates/8CPE.pdb
hmmstuff-1.0.0.dist-info/METADATA
hmmstuff-1.0.0.dist-info/WHEEL
hmmstuff-1.0.0.dist-info/top_level.txt
hmmstuff-1.0.0.dist-info/RECORD
