Metadata-Version: 2.1
Name: hmmstuff
Version: 1.0.0
Summary: A tool to get structural information about light chain amyloids
Home-page: https://github.com/grogdrinker/hmmstuff
Author: Gabriele Orlando
Author-email: gabriele.orlando@kuleuven.be
Classifier: Programming Language :: Python :: 3
Classifier: Operating System :: OS Independent
Requires-Python: <3.8
Requires-Dist: pomegranate==0.14.0
Requires-Dist: numpy
Requires-Dist: scikit-learn
Requires-Dist: Bio
